symmeplot/__init__.py
symmeplot/_version.py
symmeplot/core/__init__.py
symmeplot/core/artists.py
symmeplot/core/plot_base.py
symmeplot/core/plot_objects.py
symmeplot/core/scene.py
symmeplot/matplotlib/__init__.py
symmeplot/matplotlib/artists.py
symmeplot/matplotlib/plot_base.py
symmeplot/matplotlib/plot_objects.py
symmeplot/matplotlib/scene.py
symmeplot/pyqtgraph/__init__.py
symmeplot/pyqtgraph/artists.py
symmeplot/pyqtgraph/plot_base.py
symmeplot/pyqtgraph/plot_objects.py
symmeplot/pyqtgraph/scene.py
symmeplot/utilities/__init__.py
symmeplot/utilities/dummy_backend.py
symmeplot/utilities/sympy_patches.py
symmeplot/utilities/testing.py
symmeplot/utilities/utilities.py
symmeplot-0.2.2.dist-info/METADATA
symmeplot-0.2.2.dist-info/WHEEL
symmeplot-0.2.2.dist-info/licenses/LICENSE
symmeplot-0.2.2.dist-info/RECORD
