Metadata-Version: 2.4
Name: symmeplot
Version: 0.2.2
Summary: SymPy Mechanics Plotter
Project-URL: Homepage, https://github.com/tjstienstra/symmeplot
Project-URL: Bug Tracker, https://github.com/tjstienstra/symmeplot/issues
Project-URL: Documentation, https://tjstienstra.github.io/symmeplot/
Author-email: tjstienstra <timostienstra00@gmail.com>
License-File: LICENSE
Classifier: License :: OSI Approved :: MIT License
Classifier: Operating System :: OS Independent
Classifier: Programming Language :: Python :: 3
Requires-Python: >=3.10
Requires-Dist: numpy
Requires-Dist: sympy>=1.12
Provides-Extra: docs
Requires-Dist: autodocsumm>=0.2; extra == 'docs'
Requires-Dist: furo>=2025; extra == 'docs'
Requires-Dist: ipykernel>=7; extra == 'docs'
Requires-Dist: jupyter-sphinx>=0.5; extra == 'docs'
Requires-Dist: sphinx<9,>=8; extra == 'docs'
Provides-Extra: lint
Requires-Dist: ruff<0.15,>=0.14; extra == 'lint'
Provides-Extra: mpl-backend
Requires-Dist: matplotlib; extra == 'mpl-backend'
Provides-Extra: pg-backend
Requires-Dist: pyopengl; extra == 'pg-backend'
Requires-Dist: pyqt6; extra == 'pg-backend'
Requires-Dist: pyqtgraph; extra == 'pg-backend'
Provides-Extra: test
Requires-Dist: pytest-mock>=3.15; extra == 'test'
Requires-Dist: pytest>=9; extra == 'test'
